shortwing/__init__.py
shortwing/cli.py
shortwing/config.py
shortwing/core.py
shortwing/exceptions.py
shortwing/output.py
shortwing-0.2.1.dist-info/METADATA
shortwing-0.2.1.dist-info/WHEEL
shortwing-0.2.1.dist-info/entry_points.txt
shortwing-0.2.1.dist-info/licenses/LICENSE
shortwing-0.2.1.dist-info/RECORD
