Metadata-Version: 2.4
Name: shortwing
Version: 0.2.1
Summary: Lightweight async CLI for Dimensions DSL queries
License: MIT
License-File: LICENSE
Keywords: async,cli,dimensions,dsl,research
Classifier: Development Status :: 4 - Beta
Classifier: Environment :: Console
Classifier: Intended Audience :: Science/Research
Classifier: License :: OSI Approved :: MIT License
Classifier: Programming Language :: Python :: 3
Classifier: Programming Language :: Python :: 3.9
Classifier: Programming Language :: Python :: 3.10
Classifier: Programming Language :: Python :: 3.11
Classifier: Programming Language :: Python :: 3.12
Classifier: Programming Language :: Python :: 3.13
Requires-Python: >=3.10
Requires-Dist: click>=8.3.1
Requires-Dist: httpx>=0.27.0
